enforce_type_annotations/__init__.py
enforce_type_annotations/checker.py
flake8_enforce_type_annotations-0.1.1.dist-info/LICENSE
flake8_enforce_type_annotations-0.1.1.dist-info/METADATA
flake8_enforce_type_annotations-0.1.1.dist-info/WHEEL
flake8_enforce_type_annotations-0.1.1.dist-info/entry_points.txt
flake8_enforce_type_annotations-0.1.1.dist-info/top_level.txt
flake8_enforce_type_annotations-0.1.1.dist-info/RECORD
